rxn/reaction_preprocessing/__init__.py
rxn/reaction_preprocessing/augmenter.py
rxn/reaction_preprocessing/cleaner.py
rxn/reaction_preprocessing/config.py
rxn/reaction_preprocessing/importer.py
rxn/reaction_preprocessing/main.py
rxn/reaction_preprocessing/mixed_reaction_filter.py
rxn/reaction_preprocessing/molecule_standardizer.py
rxn/reaction_preprocessing/pistachio_record_standardizer.py
rxn/reaction_preprocessing/preprocessor.py
rxn/reaction_preprocessing/py.typed
rxn/reaction_preprocessing/reaction_standardizer.py
rxn/reaction_preprocessing/smiles_tokenizer.py
rxn/reaction_preprocessing/special_tokens.py
rxn/reaction_preprocessing/stable_data_splitter.py
rxn/reaction_preprocessing/standardizer.py
rxn/reaction_preprocessing/utils.py
rxn/reaction_preprocessing/annotations/__init__.py
rxn/reaction_preprocessing/annotations/annotation_criterion.py
rxn/reaction_preprocessing/annotations/annotation_info.py
rxn/reaction_preprocessing/annotations/missing_annotation_detector.py
rxn/reaction_preprocessing/annotations/molecule_annotation.py
rxn/reaction_preprocessing/annotations/molecule_replacer.py
rxn/reaction_preprocessing/annotations/rejected_molecules_filter.py
rxn/reaction_preprocessing/data/standardization-files/catalyst-annotation-210428.json
rxn/reaction_preprocessing/data/standardization-files/catalyst-annotation-210826.json
rxn/reaction_preprocessing/data/standardization-files/pistachio-200302.json
rxn/reaction_preprocessing/data/standardization-files/pistachio-210428.json
rxn/reaction_preprocessing/scripts/__init__.py
rxn/reaction_preprocessing/scripts/annotation_check.py
rxn/reaction_preprocessing/scripts/combine_class_token.py
rxn/reaction_preprocessing/scripts/find_missing_annotations.py
rxn/reaction_preprocessing/scripts/standardize_pistachio_records.py
rxn_reaction_preprocessing-2.6.0.dist-info/licenses/LICENSE
rxn_reaction_preprocessing-2.6.0.dist-info/METADATA
rxn_reaction_preprocessing-2.6.0.dist-info/WHEEL
rxn_reaction_preprocessing-2.6.0.dist-info/entry_points.txt
rxn_reaction_preprocessing-2.6.0.dist-info/top_level.txt
rxn_reaction_preprocessing-2.6.0.dist-info/RECORD
