Metadata-Version: 2.4
Name: rxn-reaction-preprocessing
Version: 2.6.0
Summary: Reaction preprocessing tools
Home-page: https://github.com/rxn4chemistry/rxn-reaction-preprocessing
Author: IBM RXN team
Author-email: rxn4chemistry@zurich.ibm.com
License: MIT
Project-URL: Documentation, https://rxn4chemistry.github.io/rxn-reaction-preprocessing/
Project-URL: Repository, https://github.com/rxn4chemistry/rxn-reaction-preprocessing
Classifier: Intended Audience :: Developers
Classifier: Intended Audience :: Science/Research
Classifier: Programming Language :: Python :: 3
Classifier: Programming Language :: Python :: 3.7
Classifier: Programming Language :: Python :: 3.8
Classifier: Programming Language :: Python :: 3.9
Classifier: Programming Language :: Python :: 3.10
Classifier: Programming Language :: Python :: 3.11
Classifier: Topic :: Software Development :: Libraries :: Python Modules
Requires-Python: >=3.7
License-File: LICENSE
Requires-Dist: attrs>=21.2.0
Requires-Dist: click>=7.1.2
Requires-Dist: hydra-core>=1.1.0
Requires-Dist: numpy>=1.16.5
Requires-Dist: pandas>=1.1.1
Requires-Dist: rxn-chem-utils>=1.0.4
Requires-Dist: rxn-utils>=1.5.0
Requires-Dist: tabulate>=0.8.7
Requires-Dist: xxhash>=2.0.0
Provides-Extra: dev
Requires-Dist: black>=22.3.0; extra == "dev"
Requires-Dist: bump2version>=1.0.1; extra == "dev"
Requires-Dist: flake8>=3.8.4; extra == "dev"
Requires-Dist: isort>=5.9.3; extra == "dev"
Requires-Dist: mypy>=0.950; extra == "dev"
Requires-Dist: pre-commit>=2.9.2; extra == "dev"
Requires-Dist: pylint>=2.6.0; extra == "dev"
Requires-Dist: pytest-cov>=2.10.1; extra == "dev"
Requires-Dist: pytest>=6.1.2; extra == "dev"
Requires-Dist: types-click>=7.1.1; extra == "dev"
Requires-Dist: types-dataclasses>=0.1.4; extra == "dev"
Requires-Dist: types-setuptools>=57.4.2; extra == "dev"
Requires-Dist: types-tabulate>=0.1.0; extra == "dev"
Provides-Extra: rdkit
Requires-Dist: rdkit>=2022.3.3; extra == "rdkit"
Dynamic: license-file
